mergedeep/__init__.py
mergedeep/mergedeep.py
mergedeep/test_mergedeep.py
mergedeep-1.3.3.dist-info/LICENSE
mergedeep-1.3.3.dist-info/METADATA
mergedeep-1.3.3.dist-info/WHEEL
mergedeep-1.3.3.dist-info/top_level.txt
mergedeep-1.3.3.dist-info/RECORD
