Metadata-Version: 2.1
Name: mergedeep
Version: 1.3.3
Summary: A deep merge function for 🐍.
Home-page: https://github.com/clarketm/mergedeep
Author: Travis Clarke
Author-email: travis.m.clarke@gmail.com
License: UNKNOWN
Platform: UNKNOWN
Classifier: Programming Language :: Python :: 3
Classifier: Programming Language :: Python :: 3.6
Classifier: Programming Language :: Python :: 3.7
Classifier: Programming Language :: Python :: 3.8
Classifier: Programming Language :: Python :: 3.9
Classifier: License :: OSI Approved :: MIT License
Classifier: Operating System :: OS Independent
Requires-Python: >=3.6
